markdown_subtemplate/__init__.py
markdown_subtemplate/engine.py
markdown_subtemplate/exceptions.py
markdown_subtemplate/caching/__init__.py
markdown_subtemplate/caching/cache_entry.py
markdown_subtemplate/caching/memory_cache.py
markdown_subtemplate/caching/subtemplate_cache.py
markdown_subtemplate/infrastructure/__init__.py
markdown_subtemplate/infrastructure/markdown_transformer.py
markdown_subtemplate/infrastructure/page.py
markdown_subtemplate/logging/__init__.py
markdown_subtemplate/logging/log_level.py
markdown_subtemplate/logging/null_logger.py
markdown_subtemplate/logging/stdout_logger.py
markdown_subtemplate/logging/subtemplate_logger.py
markdown_subtemplate/storage/__init__.py
markdown_subtemplate/storage/file_storage.py
markdown_subtemplate/storage/subtemplate_storage.py
markdown_subtemplate-0.2.22.dist-info/LICENSE
markdown_subtemplate-0.2.22.dist-info/METADATA
markdown_subtemplate-0.2.22.dist-info/WHEEL
markdown_subtemplate-0.2.22.dist-info/top_level.txt
markdown_subtemplate-0.2.22.dist-info/RECORD
