Metadata-Version: 2.1
Name: markdown-subtemplate
Version: 0.2.22
Summary: A template engine to render Markdown with external template imports and variable replacements.
Home-page: https://github.com/mikeckennedy/markdown-subtemplate
Author: Michael Kennedy
Author-email: michael@talkpython.fm
License: MIT
Platform: UNKNOWN
Classifier: Development Status :: 3 - Alpha
Classifier: License :: OSI Approved :: MIT License
Classifier: Programming Language :: Python
Classifier: Programming Language :: Python :: 3
Classifier: Programming Language :: Python :: 3.6
Classifier: Programming Language :: Python :: 3.7
Classifier: Programming Language :: Python :: 3.8
Requires-Dist: markdown2
